{
  "createdAt": "2026-05-03T13:49:57.496498",
  "universe": "VN100 local universe",
  "method": "Monthly technical indicator cache from monthly OHLC. Web reads output only. MA row uses MA10/20/50.",
  "universeCount": 95,
  "count": 95,
  "errorCount": 0,
  "items": [
    {
      "symbol": "FPT",
      "date": "2026-04-30",
      "monthlyBars": 18,
      "rsi14Month": 50.19,
      "adx14Month": 58.89,
      "plusDiMonth": 12.07,
      "minusDiMonth": 30.24,
      "ma10Month": 93.78,
      "ma20Month": null,
      "ma50Month": null,
      "bbUpperMonth": 115.26,
      "bbLowerMonth": 72.31,
      "bbMiddleMonth": 93.78,
      "bbPercentMonth": 0.074,
      "macdMonth": -9.4422,
      "signalMonth": -6.873,
      "histogramMonth": -2.5692
    },
    {
      "symbol": "MWG",
      "date": "2026-04-30",
      "monthlyBars": 18,
      "rsi14Month": 67.61,
      "adx14Month": 54.86,
      "plusDiMonth": 23.1,
      "minusDiMonth": 15.83,
      "ma10Month": 82.37,
      "ma20Month": null,
      "ma50Month": null,
      "bbUpperMonth": 98.75,
      "bbLowerMonth": 65.99,
      "bbMiddleMonth": 82.37,
      "bbPercentMonth": 0.55,
      "macdMonth": 7.3394,
      "signalMonth": 5.6149,
      "histogramMonth": 1.7245
    },
    {
      "symbol": "HPG",
      "date": "2026-04-30",
      "monthlyBars": 18,
      "rsi14Month": 62.9,
      "adx14Month": 51.71,
      "plusDiMonth": 21.79,
      "minusDiMonth": 14.01,
      "ma10Month": 27.05,
      "ma20Month": null,
      "ma50Month": null,
      "bbUpperMonth": 29.18,
      "bbLowerMonth": 24.92,
      "bbMiddleMonth": 27.05,
      "bbPercentMonth": 0.664,
      "macdMonth": 1.4174,
      "signalMonth": 1.0906,
      "histogramMonth": 0.3268
    },
    {
      "symbol": "SSI",
      "date": "2026-04-30",
      "monthlyBars": 18,
      "rsi14Month": 61.05,
      "adx14Month": 58.06,
      "plusDiMonth": 23.49,
      "minusDiMonth": 19.48,
      "ma10Month": 31.25,
      "ma20Month": null,
      "ma50Month": null,
      "bbUpperMonth": 37.59,
      "bbLowerMonth": 24.91,
      "bbMiddleMonth": 31.25,
      "bbPercentMonth": 0.216,
      "macdMonth": 2.0393,
      "signalMonth": 2.0865,
      "histogramMonth": -0.0472
    },
    {
      "symbol": "VCI",
      "date": "2026-04-30",
      "monthlyBars": 18,
      "rsi14Month": 50.26,
      "adx14Month": 47.06,
      "plusDiMonth": 23.66,
      "minusDiMonth": 13.74,
      "ma10Month": 28.28,
      "ma20Month": null,
      "ma50Month": null,
      "bbUpperMonth": 34.81,
      "bbLowerMonth": 21.75,
      "bbMiddleMonth": 28.28,
      "bbPercentMonth": 0.341,
      "macdMonth": 0.6567,
      "signalMonth": 0.9195,
      "histogramMonth": -0.2628
    },
    {
      "symbol": "VND",
      "date": "2026-04-30",
      "monthlyBars": 18,
      "rsi14Month": 38.79,
      "adx14Month": 53.74,
      "plusDiMonth": 22.59,
      "minusDiMonth": 21.74,
      "ma10Month": 19.85,
      "ma20Month": null,
      "ma50Month": null,
      "bbUpperMonth": 26.28,
      "bbLowerMonth": 13.42,
      "bbMiddleMonth": 19.85,
      "bbPercentMonth": 0.208,
      "macdMonth": 1.0956,
      "signalMonth": 1.4436,
      "histogramMonth": -0.348
    },
    {
      "symbol": "HCM",
      "date": "2026-04-30",
      "monthlyBars": 18,
      "rsi14Month": 66.89,
      "adx14Month": 49.46,
      "plusDiMonth": 27.57,
      "minusDiMonth": 19.72,
      "ma10Month": 24.39,
      "ma20Month": null,
      "ma50Month": null,
      "bbUpperMonth": 28.97,
      "bbLowerMonth": 19.82,
      "bbMiddleMonth": 24.39,
      "bbPercentMonth": 0.758,
      "macdMonth": 0.7143,
      "signalMonth": 0.5524,
      "histogramMonth": 0.162
    },
    {
      "symbol": "MBS",
      "date": "2026-04-30",
      "monthlyBars": 18,
      "rsi14Month": 49.25,
      "adx14Month": 47.1,
      "plusDiMonth": 17.13,
      "minusDiMonth": 20.1,
      "ma10Month": 23.24,
      "ma20Month": null,
      "ma50Month": null,
      "bbUpperMonth": 30.27,
      "bbLowerMonth": 16.21,
      "bbMiddleMonth": 23.24,
      "bbPercentMonth": 0.227,
      "macdMonth": 0.2593,
      "signalMonth": 0.6837,
      "histogramMonth": -0.4244
    },
    {
      "symbol": "TCB",
      "date": "2026-04-30",
      "monthlyBars": 18,
      "rsi14Month": 65.78,
      "adx14Month": 56.97,
      "plusDiMonth": 21.64,
      "minusDiMonth": 22.12,
      "ma10Month": 35.0,
      "ma20Month": null,
      "ma50Month": null,
      "bbUpperMonth": 39.63,
      "bbLowerMonth": 30.37,
      "bbMiddleMonth": 35.0,
      "bbPercentMonth": 0.376,
      "macdMonth": 2.8216,
      "signalMonth": 2.8372,
      "histogramMonth": -0.0156
    },
    {
      "symbol": "MBB",
      "date": "2026-04-30",
      "monthlyBars": 18,
      "rsi14Month": 70.71,
      "adx14Month": 65.4,
      "plusDiMonth": 35.43,
      "minusDiMonth": 14.6,
      "ma10Month": 25.49,
      "ma20Month": null,
      "ma50Month": null,
      "bbUpperMonth": 30.27,
      "bbLowerMonth": 20.71,
      "bbMiddleMonth": 25.49,
      "bbPercentMonth": 0.559,
      "macdMonth": 2.8269,
      "signalMonth": 2.3039,
      "histogramMonth": 0.523
    },
    {
      "symbol": "ACB",
      "date": "2026-04-30",
      "monthlyBars": 18,
      "rsi14Month": 62.24,
      "adx14Month": 53.15,
      "plusDiMonth": 23.27,
      "minusDiMonth": 20.56,
      "ma10Month": 24.57,
      "ma20Month": null,
      "ma50Month": null,
      "bbUpperMonth": 27.36,
      "bbLowerMonth": 21.79,
      "bbMiddleMonth": 24.57,
      "bbPercentMonth": 0.307,
      "macdMonth": 0.789,
      "signalMonth": 0.7839,
      "histogramMonth": 0.0051
    },
    {
      "symbol": "CTG",
      "date": "2026-04-30",
      "monthlyBars": 18,
      "rsi14Month": 73.25,
      "adx14Month": 66.61,
      "plusDiMonth": 31.43,
      "minusDiMonth": 14.62,
      "ma10Month": 35.16,
      "ma20Month": null,
      "ma50Month": null,
      "bbUpperMonth": 39.38,
      "bbLowerMonth": 30.94,
      "bbMiddleMonth": 35.16,
      "bbPercentMonth": 0.475,
      "macdMonth": 2.978,
      "signalMonth": 2.5296,
      "histogramMonth": 0.4483
    },
    {
      "symbol": "BID",
      "date": "2026-04-30",
      "monthlyBars": 18,
      "rsi14Month": 45.37,
      "adx14Month": 56.89,
      "plusDiMonth": 30.13,
      "minusDiMonth": 18.77,
      "ma10Month": 41.41,
      "ma20Month": null,
      "ma50Month": null,
      "bbUpperMonth": 52.26,
      "bbLowerMonth": 30.55,
      "bbMiddleMonth": 41.41,
      "bbPercentMonth": 0.44,
      "macdMonth": 1.2555,
      "signalMonth": 0.8279,
      "histogramMonth": 0.4276
    },
    {
      "symbol": "VPB",
      "date": "2026-04-30",
      "monthlyBars": 18,
      "rsi14Month": 57.98,
      "adx14Month": 67.04,
      "plusDiMonth": 28.92,
      "minusDiMonth": 14.72,
      "ma10Month": 28.87,
      "ma20Month": null,
      "ma50Month": null,
      "bbUpperMonth": 34.17,
      "bbLowerMonth": 23.56,
      "bbMiddleMonth": 28.87,
      "bbPercentMonth": 0.277,
      "macdMonth": 2.515,
      "signalMonth": 2.2986,
      "histogramMonth": 0.2164
    },
    {
      "symbol": "STB",
      "date": "2026-04-30",
      "monthlyBars": 18,
      "rsi14Month": 83.39,
      "adx14Month": 70.36,
      "plusDiMonth": 28.2,
      "minusDiMonth": 6.75,
      "ma10Month": 58.27,
      "ma20Month": null,
      "ma50Month": null,
      "bbUpperMonth": 70.83,
      "bbLowerMonth": 45.72,
      "bbMiddleMonth": 58.27,
      "bbPercentMonth": 0.867,
      "macdMonth": 7.8155,
      "signalMonth": 5.9013,
      "histogramMonth": 1.9143
    },
    {
      "symbol": "VIB",
      "date": "2026-04-30",
      "monthlyBars": 18,
      "rsi14Month": 59.52,
      "adx14Month": 57.86,
      "plusDiMonth": 26.63,
      "minusDiMonth": 19.47,
      "ma10Month": 17.63,
      "ma20Month": null,
      "ma50Month": null,
      "bbUpperMonth": 20.86,
      "bbLowerMonth": 14.4,
      "bbMiddleMonth": 17.63,
      "bbPercentMonth": 0.294,
      "macdMonth": 0.334,
      "signalMonth": 0.4848,
      "histogramMonth": -0.1508
    },
    {
      "symbol": "VHM",
      "date": "2026-04-30",
      "monthlyBars": 18,
      "rsi14Month": 78.02,
      "adx14Month": 86.11,
      "plusDiMonth": 50.68,
      "minusDiMonth": 8.15,
      "ma10Month": 108.66,
      "ma20Month": null,
      "ma50Month": null,
      "bbUpperMonth": 139.85,
      "bbLowerMonth": 77.47,
      "bbMiddleMonth": 108.66,
      "bbPercentMonth": 1.099,
      "macdMonth": 20.6897,
      "signalMonth": 15.9969,
      "histogramMonth": 4.6928
    },
    {
      "symbol": "VIC",
      "date": "2026-04-30",
      "monthlyBars": 18,
      "rsi14Month": 77.37,
      "adx14Month": 95.09,
      "plusDiMonth": 41.63,
      "minusDiMonth": 3.9,
      "ma10Month": 126.12,
      "ma20Month": null,
      "ma50Month": null,
      "bbUpperMonth": 228.7,
      "bbLowerMonth": 23.53,
      "bbMiddleMonth": 126.12,
      "bbPercentMonth": 0.928,
      "macdMonth": 39.5812,
      "signalMonth": 25.9383,
      "histogramMonth": 13.6429
    },
    {
      "symbol": "VRE",
      "date": "2026-04-30",
      "monthlyBars": 18,
      "rsi14Month": 57.91,
      "adx14Month": 78.66,
      "plusDiMonth": 33.6,
      "minusDiMonth": 12.06,
      "ma10Month": 30.91,
      "ma20Month": null,
      "ma50Month": null,
      "bbUpperMonth": 36.35,
      "bbLowerMonth": 25.47,
      "bbMiddleMonth": 30.91,
      "bbPercentMonth": 0.628,
      "macdMonth": 3.2781,
      "signalMonth": 3.1108,
      "histogramMonth": 0.1673
    },
    {
      "symbol": "KDH",
      "date": "2026-04-30",
      "monthlyBars": 18,
      "rsi14Month": 59.07,
      "adx14Month": 51.45,
      "plusDiMonth": 13.73,
      "minusDiMonth": 24.56,
      "ma10Month": 30.62,
      "ma20Month": null,
      "ma50Month": null,
      "bbUpperMonth": 39.36,
      "bbLowerMonth": 21.88,
      "bbMiddleMonth": 30.62,
      "bbPercentMonth": 0.202,
      "macdMonth": -0.6098,
      "signalMonth": 0.0125,
      "histogramMonth": -0.6223
    },
    {
      "symbol": "DXG",
      "date": "2026-04-30",
      "monthlyBars": 18,
      "rsi14Month": 32.09,
      "adx14Month": 47.0,
      "plusDiMonth": 22.39,
      "minusDiMonth": 25.1,
      "ma10Month": 17.99,
      "ma20Month": null,
      "ma50Month": null,
      "bbUpperMonth": 23.73,
      "bbLowerMonth": 12.24,
      "bbMiddleMonth": 17.99,
      "bbPercentMonth": 0.271,
      "macdMonth": 0.4119,
      "signalMonth": 0.7708,
      "histogramMonth": -0.3589
    },
    {
      "symbol": "NVL",
      "date": "2026-04-30",
      "monthlyBars": 18,
      "rsi14Month": 62.56,
      "adx14Month": 49.4,
      "plusDiMonth": 27.66,
      "minusDiMonth": 19.27,
      "ma10Month": 15.05,
      "ma20Month": null,
      "ma50Month": null,
      "bbUpperMonth": 19.89,
      "bbLowerMonth": 10.2,
      "bbMiddleMonth": 15.05,
      "bbPercentMonth": 1.063,
      "macdMonth": 1.2357,
      "signalMonth": 0.88,
      "histogramMonth": 0.3557
    },
    {
      "symbol": "KBC",
      "date": "2026-04-30",
      "monthlyBars": 18,
      "rsi14Month": 51.16,
      "adx14Month": 54.59,
      "plusDiMonth": 19.2,
      "minusDiMonth": 21.55,
      "ma10Month": 34.92,
      "ma20Month": null,
      "ma50Month": null,
      "bbUpperMonth": 39.4,
      "bbLowerMonth": 30.43,
      "bbMiddleMonth": 34.92,
      "bbPercentMonth": 0.387,
      "macdMonth": 1.7636,
      "signalMonth": 1.5981,
      "histogramMonth": 0.1656
    },
    {
      "symbol": "GEX",
      "date": "2026-04-30",
      "monthlyBars": 18,
      "rsi14Month": 57.96,
      "adx14Month": 75.89,
      "plusDiMonth": 30.24,
      "minusDiMonth": 12.34,
      "ma10Month": 45.45,
      "ma20Month": null,
      "ma50Month": null,
      "bbUpperMonth": 61.44,
      "bbLowerMonth": 29.45,
      "bbMiddleMonth": 45.45,
      "bbPercentMonth": 0.302,
      "macdMonth": 5.7148,
      "signalMonth": 6.3343,
      "histogramMonth": -0.6196
    },
    {
      "symbol": "GVR",
      "date": "2026-04-30",
      "monthlyBars": 18,
      "rsi14Month": 48.82,
      "adx14Month": 51.1,
      "plusDiMonth": 22.3,
      "minusDiMonth": 21.13,
      "ma10Month": 31.3,
      "ma20Month": null,
      "ma50Month": null,
      "bbUpperMonth": 41.4,
      "bbLowerMonth": 21.2,
      "bbMiddleMonth": 31.3,
      "bbPercentMonth": 0.619,
      "macdMonth": 0.9006,
      "signalMonth": 0.1765,
      "histogramMonth": 0.7242
    },
    {
      "symbol": "PNJ",
      "date": "2026-04-30",
      "monthlyBars": 18,
      "rsi14Month": 62.96,
      "adx14Month": 57.49,
      "plusDiMonth": 25.43,
      "minusDiMonth": 11.09,
      "ma10Month": 65.72,
      "ma20Month": null,
      "ma50Month": null,
      "bbUpperMonth": 87.07,
      "bbLowerMonth": 44.36,
      "bbMiddleMonth": 65.72,
      "bbPercentMonth": 0.537,
      "macdMonth": 3.4578,
      "signalMonth": 1.5925,
      "histogramMonth": 1.8652
    },
    {
      "symbol": "VNM",
      "date": "2026-04-30",
      "monthlyBars": 18,
      "rsi14Month": 47.62,
      "adx14Month": 56.6,
      "plusDiMonth": 23.92,
      "minusDiMonth": 21.56,
      "ma10Month": 61.64,
      "ma20Month": null,
      "ma50Month": null,
      "bbUpperMonth": 70.88,
      "bbLowerMonth": 52.39,
      "bbMiddleMonth": 61.64,
      "bbPercentMonth": 0.46,
      "macdMonth": 1.3473,
      "signalMonth": 0.695,
      "histogramMonth": 0.6523
    },
    {
      "symbol": "MSN",
      "date": "2026-04-30",
      "monthlyBars": 18,
      "rsi14Month": 39.35,
      "adx14Month": 50.6,
      "plusDiMonth": 19.48,
      "minusDiMonth": 18.33,
      "ma10Month": 78.58,
      "ma20Month": null,
      "ma50Month": null,
      "bbUpperMonth": 85.56,
      "bbLowerMonth": 71.6,
      "bbMiddleMonth": 78.58,
      "bbPercentMonth": 0.372,
      "macdMonth": 1.7021,
      "signalMonth": 1.2731,
      "histogramMonth": 0.429
    },
    {
      "symbol": "SAB",
      "date": "2026-04-30",
      "monthlyBars": 18,
      "rsi14Month": 61.95,
      "adx14Month": 56.57,
      "plusDiMonth": 23.4,
      "minusDiMonth": 20.01,
      "ma10Month": 45.93,
      "ma20Month": null,
      "ma50Month": null,
      "bbUpperMonth": 50.27,
      "bbLowerMonth": 41.59,
      "bbMiddleMonth": 45.93,
      "bbPercentMonth": 0.681,
      "macdMonth": -0.3909,
      "signalMonth": -0.6843,
      "histogramMonth": 0.2934
    },
    {
      "symbol": "GAS",
      "date": "2026-04-30",
      "monthlyBars": 18,
      "rsi14Month": 49.1,
      "adx14Month": 58.73,
      "plusDiMonth": 31.8,
      "minusDiMonth": 22.2,
      "ma10Month": 76.37,
      "ma20Month": null,
      "ma50Month": null,
      "bbUpperMonth": 116.51,
      "bbLowerMonth": 36.23,
      "bbMiddleMonth": 76.37,
      "bbPercentMonth": 0.485,
      "macdMonth": 5.5928,
      "signalMonth": 3.1441,
      "histogramMonth": 2.4487
    },
    {
      "symbol": "PLX",
      "date": "2026-04-30",
      "monthlyBars": 18,
      "rsi14Month": 39.89,
      "adx14Month": 51.06,
      "plusDiMonth": 28.13,
      "minusDiMonth": 18.73,
      "ma10Month": 40.45,
      "ma20Month": null,
      "ma50Month": null,
      "bbUpperMonth": 59.69,
      "bbLowerMonth": 21.22,
      "bbMiddleMonth": 40.45,
      "bbPercentMonth": 0.414,
      "macdMonth": 1.4483,
      "signalMonth": 0.6633,
      "histogramMonth": 0.785
    },
    {
      "symbol": "PVD",
      "date": "2026-04-30",
      "monthlyBars": 18,
      "rsi14Month": 58.32,
      "adx14Month": 55.85,
      "plusDiMonth": 40.16,
      "minusDiMonth": 13.09,
      "ma10Month": 27.57,
      "ma20Month": null,
      "ma50Month": null,
      "bbUpperMonth": 40.17,
      "bbLowerMonth": 14.97,
      "bbMiddleMonth": 27.57,
      "bbPercentMonth": 0.636,
      "macdMonth": 2.6175,
      "signalMonth": 1.1532,
      "histogramMonth": 1.4644
    },
    {
      "symbol": "PVS",
      "date": "2026-04-30",
      "monthlyBars": 18,
      "rsi14Month": 53.28,
      "adx14Month": 54.14,
      "plusDiMonth": 30.21,
      "minusDiMonth": 12.89,
      "ma10Month": 36.32,
      "ma20Month": null,
      "ma50Month": null,
      "bbUpperMonth": 48.87,
      "bbLowerMonth": 23.78,
      "bbMiddleMonth": 36.32,
      "bbPercentMonth": 0.567,
      "macdMonth": 2.3708,
      "signalMonth": 1.0927,
      "histogramMonth": 1.2781
    },
    {
      "symbol": "DGC",
      "date": "2026-04-30",
      "monthlyBars": 18,
      "rsi14Month": 45.23,
      "adx14Month": 65.62,
      "plusDiMonth": 7.07,
      "minusDiMonth": 33.82,
      "ma10Month": 77.77,
      "ma20Month": null,
      "ma50Month": null,
      "bbUpperMonth": 112.37,
      "bbLowerMonth": 43.17,
      "bbMiddleMonth": 77.77,
      "bbPercentMonth": 0.151,
      "macdMonth": -11.1715,
      "signalMonth": -6.7934,
      "histogramMonth": -4.3781
    },
    {
      "symbol": "DCM",
      "date": "2026-04-30",
      "monthlyBars": 18,
      "rsi14Month": 52.41,
      "adx14Month": 53.23,
      "plusDiMonth": 37.92,
      "minusDiMonth": 16.89,
      "ma10Month": 38.48,
      "ma20Month": null,
      "ma50Month": null,
      "bbUpperMonth": 48.23,
      "bbLowerMonth": 28.72,
      "bbMiddleMonth": 38.48,
      "bbPercentMonth": 0.717,
      "macdMonth": 2.0042,
      "signalMonth": 0.7817,
      "histogramMonth": 1.2226
    },
    {
      "symbol": "DPM",
      "date": "2026-04-30",
      "monthlyBars": 18,
      "rsi14Month": 58.73,
      "adx14Month": 56.0,
      "plusDiMonth": 43.47,
      "minusDiMonth": 17.57,
      "ma10Month": 25.27,
      "ma20Month": null,
      "ma50Month": null,
      "bbUpperMonth": 29.98,
      "bbLowerMonth": 20.55,
      "bbMiddleMonth": 25.27,
      "bbPercentMonth": 0.631,
      "macdMonth": 1.9104,
      "signalMonth": 1.2894,
      "histogramMonth": 0.6211
    },
    {
      "symbol": "HSG",
      "date": "2026-04-30",
      "monthlyBars": 18,
      "rsi14Month": 36.75,
      "adx14Month": 55.14,
      "plusDiMonth": 13.14,
      "minusDiMonth": 25.84,
      "ma10Month": 16.82,
      "ma20Month": null,
      "ma50Month": null,
      "bbUpperMonth": 19.59,
      "bbLowerMonth": 14.06,
      "bbMiddleMonth": 16.82,
      "bbPercentMonth": 0.342,
      "macdMonth": -0.6165,
      "signalMonth": -0.456,
      "histogramMonth": -0.1605
    },
    {
      "symbol": "NKG",
      "date": "2026-04-30",
      "monthlyBars": 18,
      "rsi14Month": 38.44,
      "adx14Month": 46.07,
      "plusDiMonth": 16.06,
      "minusDiMonth": 19.34,
      "ma10Month": 15.58,
      "ma20Month": null,
      "ma50Month": null,
      "bbUpperMonth": 17.72,
      "bbLowerMonth": 13.45,
      "bbMiddleMonth": 15.58,
      "bbPercentMonth": 0.211,
      "macdMonth": -0.0035,
      "signalMonth": 0.0689,
      "histogramMonth": -0.0724
    },
    {
      "symbol": "DIG",
      "date": "2026-04-30",
      "monthlyBars": 18,
      "rsi14Month": 29.69,
      "adx14Month": 48.62,
      "plusDiMonth": 17.59,
      "minusDiMonth": 26.99,
      "ma10Month": 18.07,
      "ma20Month": null,
      "ma50Month": null,
      "bbUpperMonth": 24.0,
      "bbLowerMonth": 12.15,
      "bbMiddleMonth": 18.07,
      "bbPercentMonth": 0.215,
      "macdMonth": -0.4109,
      "signalMonth": 0.0235,
      "histogramMonth": -0.4344
    },
    {
      "symbol": "CEO",
      "date": "2026-04-30",
      "monthlyBars": 18,
      "rsi14Month": 41.67,
      "adx14Month": 54.3,
      "plusDiMonth": 22.25,
      "minusDiMonth": 21.65,
      "ma10Month": 21.79,
      "ma20Month": null,
      "ma50Month": null,
      "bbUpperMonth": 28.79,
      "bbLowerMonth": 14.78,
      "bbMiddleMonth": 21.79,
      "bbPercentMonth": 0.216,
      "macdMonth": 1.5119,
      "signalMonth": 1.87,
      "histogramMonth": -0.3581
    },
    {
      "symbol": "VTP",
      "date": "2026-04-30",
      "monthlyBars": 18,
      "rsi14Month": 48.11,
      "adx14Month": 44.74,
      "plusDiMonth": 19.57,
      "minusDiMonth": 18.98,
      "ma10Month": 75.42,
      "ma20Month": null,
      "ma50Month": null,
      "bbUpperMonth": 86.76,
      "bbLowerMonth": 64.09,
      "bbMiddleMonth": 75.42,
      "bbPercentMonth": 0.173,
      "macdMonth": -6.3991,
      "signalMonth": -4.9536,
      "histogramMonth": -1.4455
    },
    {
      "symbol": "CTR",
      "date": "2026-04-30",
      "monthlyBars": 18,
      "rsi14Month": 52.7,
      "adx14Month": 54.57,
      "plusDiMonth": 18.16,
      "minusDiMonth": 23.62,
      "ma10Month": 88.87,
      "ma20Month": null,
      "ma50Month": null,
      "bbUpperMonth": 97.33,
      "bbLowerMonth": 80.41,
      "bbMiddleMonth": 88.87,
      "bbPercentMonth": 0.325,
      "macdMonth": -7.0209,
      "signalMonth": -6.64,
      "histogramMonth": -0.3809
    },
    {
      "symbol": "REE",
      "date": "2026-04-30",
      "monthlyBars": 18,
      "rsi14Month": 52.48,
      "adx14Month": 43.17,
      "plusDiMonth": 26.83,
      "minusDiMonth": 15.18,
      "ma10Month": 63.52,
      "ma20Month": null,
      "ma50Month": null,
      "bbUpperMonth": 68.89,
      "bbLowerMonth": 58.15,
      "bbMiddleMonth": 63.52,
      "bbPercentMonth": 0.2,
      "macdMonth": 1.5033,
      "signalMonth": 1.6063,
      "histogramMonth": -0.103
    },
    {
      "symbol": "PC1",
      "date": "2026-04-30",
      "monthlyBars": 18,
      "rsi14Month": 43.5,
      "adx14Month": 52.61,
      "plusDiMonth": 28.87,
      "minusDiMonth": 20.81,
      "ma10Month": 23.52,
      "ma20Month": null,
      "ma50Month": null,
      "bbUpperMonth": 30.11,
      "bbLowerMonth": 16.92,
      "bbMiddleMonth": 23.52,
      "bbPercentMonth": 0.199,
      "macdMonth": 1.1983,
      "signalMonth": 0.8489,
      "histogramMonth": 0.3494
    },
    {
      "symbol": "SZC",
      "date": "2026-04-30",
      "monthlyBars": 18,
      "rsi14Month": 47.38,
      "adx14Month": 52.57,
      "plusDiMonth": 16.22,
      "minusDiMonth": 26.55,
      "ma10Month": 31.89,
      "ma20Month": null,
      "ma50Month": null,
      "bbUpperMonth": 37.71,
      "bbLowerMonth": 26.07,
      "bbMiddleMonth": 31.89,
      "bbPercentMonth": 0.097,
      "macdMonth": -2.5595,
      "signalMonth": -1.8916,
      "histogramMonth": -0.668
    },
    {
      "symbol": "BCM",
      "date": "2026-04-30",
      "monthlyBars": 18,
      "rsi14Month": 54.49,
      "adx14Month": 45.79,
      "plusDiMonth": 22.72,
      "minusDiMonth": 25.81,
      "ma10Month": 63.37,
      "ma20Month": null,
      "ma50Month": null,
      "bbUpperMonth": 75.17,
      "bbLowerMonth": 51.58,
      "bbMiddleMonth": 63.37,
      "bbPercentMonth": 0.069,
      "macdMonth": -1.8086,
      "signalMonth": -0.5938,
      "histogramMonth": -1.2149
    },
    {
      "symbol": "HDG",
      "date": "2026-04-30",
      "monthlyBars": 18,
      "rsi14Month": 46.06,
      "adx14Month": 47.36,
      "plusDiMonth": 22.39,
      "minusDiMonth": 13.64,
      "ma10Month": 28.62,
      "ma20Month": null,
      "ma50Month": null,
      "bbUpperMonth": 33.44,
      "bbLowerMonth": 23.8,
      "bbMiddleMonth": 28.62,
      "bbPercentMonth": 0.218,
      "macdMonth": 0.6735,
      "signalMonth": 0.6578,
      "histogramMonth": 0.0158
    },
    {
      "symbol": "KSB",
      "date": "2026-04-30",
      "monthlyBars": 18,
      "rsi14Month": 60.3,
      "adx14Month": 47.25,
      "plusDiMonth": 15.05,
      "minusDiMonth": 23.49,
      "ma10Month": 17.82,
      "ma20Month": null,
      "ma50Month": null,
      "bbUpperMonth": 20.24,
      "bbLowerMonth": 15.4,
      "bbMiddleMonth": 17.82,
      "bbPercentMonth": 0.145,
      "macdMonth": -0.19,
      "signalMonth": 0.0395,
      "histogramMonth": -0.2295
    },
    {
      "symbol": "ANV",
      "date": "2026-04-30",
      "monthlyBars": 18,
      "rsi14Month": 63.72,
      "adx14Month": 58.65,
      "plusDiMonth": 24.6,
      "minusDiMonth": 16.68,
      "ma10Month": 26.47,
      "ma20Month": null,
      "ma50Month": null,
      "bbUpperMonth": 31.44,
      "bbLowerMonth": 21.5,
      "bbMiddleMonth": 26.47,
      "bbPercentMonth": 0.241,
      "macdMonth": 2.2171,
      "signalMonth": 2.0303,
      "histogramMonth": 0.1869
    },
    {
      "symbol": "VHC",
      "date": "2026-04-30",
      "monthlyBars": 18,
      "rsi14Month": 47.56,
      "adx14Month": 52.52,
      "plusDiMonth": 16.5,
      "minusDiMonth": 18.09,
      "ma10Month": 58.45,
      "ma20Month": null,
      "ma50Month": null,
      "bbUpperMonth": 64.99,
      "bbLowerMonth": 51.9,
      "bbMiddleMonth": 58.45,
      "bbPercentMonth": 0.71,
      "macdMonth": -1.7625,
      "signalMonth": -2.3747,
      "histogramMonth": 0.6123
    },
    {
      "symbol": "AAA",
      "date": "2026-04-30",
      "monthlyBars": 18,
      "rsi14Month": 52.54,
      "adx14Month": 44.94,
      "plusDiMonth": 14.57,
      "minusDiMonth": 22.6,
      "ma10Month": 7.97,
      "ma20Month": null,
      "ma50Month": null,
      "bbUpperMonth": 8.98,
      "bbLowerMonth": 6.96,
      "bbMiddleMonth": 7.97,
      "bbPercentMonth": 0.174,
      "macdMonth": -0.1384,
      "signalMonth": -0.0649,
      "histogramMonth": -0.0735
    },
    {
      "symbol": "APH",
      "date": "2026-04-30",
      "monthlyBars": 18,
      "rsi14Month": 63.44,
      "adx14Month": 45.83,
      "plusDiMonth": 15.11,
      "minusDiMonth": 21.95,
      "ma10Month": 6.4,
      "ma20Month": null,
      "ma50Month": null,
      "bbUpperMonth": 7.38,
      "bbLowerMonth": 5.42,
      "bbMiddleMonth": 6.4,
      "bbPercentMonth": 0.209,
      "macdMonth": -0.1544,
      "signalMonth": -0.0432,
      "histogramMonth": -0.1111
    },
    {
      "symbol": "BCG",
      "date": "2025-10-31",
      "monthlyBars": 18,
      "rsi14Month": 8.71,
      "adx14Month": 78.12,
      "plusDiMonth": 5.96,
      "minusDiMonth": 25.7,
      "ma10Month": 3.75,
      "ma20Month": null,
      "ma50Month": null,
      "bbUpperMonth": 6.08,
      "bbLowerMonth": 1.42,
      "bbMiddleMonth": 3.75,
      "bbPercentMonth": 0.238,
      "macdMonth": -1.4155,
      "signalMonth": -1.1894,
      "histogramMonth": -0.2261
    },
    {
      "symbol": "BIC",
      "date": "2026-04-30",
      "monthlyBars": 18,
      "rsi14Month": 48.46,
      "adx14Month": 62.37,
      "plusDiMonth": 27.37,
      "minusDiMonth": 14.15,
      "ma10Month": 24.88,
      "ma20Month": null,
      "ma50Month": null,
      "bbUpperMonth": 29.75,
      "bbLowerMonth": 20.02,
      "bbMiddleMonth": 24.88,
      "bbPercentMonth": 0.404,
      "macdMonth": 1.2389,
      "signalMonth": 1.1748,
      "histogramMonth": 0.0641
    },
    {
      "symbol": "BWE",
      "date": "2026-04-30",
      "monthlyBars": 18,
      "rsi14Month": 35.88,
      "adx14Month": 51.35,
      "plusDiMonth": 7.07,
      "minusDiMonth": 17.58,
      "ma10Month": 45.69,
      "ma20Month": null,
      "ma50Month": null,
      "bbUpperMonth": 49.05,
      "bbLowerMonth": 42.33,
      "bbMiddleMonth": 45.69,
      "bbPercentMonth": 0.174,
      "macdMonth": -0.2879,
      "signalMonth": 0.0784,
      "histogramMonth": -0.3663
    },
    {
      "symbol": "CTD",
      "date": "2026-04-30",
      "monthlyBars": 18,
      "rsi14Month": 68.45,
      "adx14Month": 55.15,
      "plusDiMonth": 25.75,
      "minusDiMonth": 13.57,
      "ma10Month": 77.92,
      "ma20Month": null,
      "ma50Month": null,
      "bbUpperMonth": 93.93,
      "bbLowerMonth": 61.91,
      "bbMiddleMonth": 77.92,
      "bbPercentMonth": 0.777,
      "macdMonth": 5.601,
      "signalMonth": 4.7351,
      "histogramMonth": 0.8659
    },
    {
      "symbol": "CTS",
      "date": "2026-04-30",
      "monthlyBars": 18,
      "rsi14Month": 45.7,
      "adx14Month": 52.98,
      "plusDiMonth": 21.0,
      "minusDiMonth": 22.38,
      "ma10Month": 34.69,
      "ma20Month": null,
      "ma50Month": null,
      "bbUpperMonth": 46.43,
      "bbLowerMonth": 22.94,
      "bbMiddleMonth": 34.69,
      "bbPercentMonth": 0.134,
      "macdMonth": 1.3552,
      "signalMonth": 2.1604,
      "histogramMonth": -0.8052
    },
    {
      "symbol": "D2D",
      "date": "2026-04-30",
      "monthlyBars": 18,
      "rsi14Month": 56.81,
      "adx14Month": 82.94,
      "plusDiMonth": 31.52,
      "minusDiMonth": 6.55,
      "ma10Month": 36.33,
      "ma20Month": null,
      "ma50Month": null,
      "bbUpperMonth": 38.25,
      "bbLowerMonth": 34.4,
      "bbMiddleMonth": 36.33,
      "bbPercentMonth": 0.129,
      "macdMonth": 2.4339,
      "signalMonth": 2.4444,
      "histogramMonth": -0.0105
    },
    {
      "symbol": "DAT",
      "date": "2026-04-30",
      "monthlyBars": 21,
      "rsi14Month": 47.99,
      "adx14Month": 66.83,
      "plusDiMonth": 29.42,
      "minusDiMonth": 7.0,
      "ma10Month": 9.16,
      "ma20Month": 8.36,
      "ma50Month": null,
      "bbUpperMonth": 10.68,
      "bbLowerMonth": 6.05,
      "bbMiddleMonth": null,
      "bbPercentMonth": 0.515,
      "macdMonth": 0.2822,
      "signalMonth": 0.2594,
      "histogramMonth": 0.0228
    },
    {
      "symbol": "DPR",
      "date": "2026-04-30",
      "monthlyBars": 18,
      "rsi14Month": 61.49,
      "adx14Month": 46.8,
      "plusDiMonth": 22.37,
      "minusDiMonth": 12.49,
      "ma10Month": 39.42,
      "ma20Month": null,
      "ma50Month": null,
      "bbUpperMonth": 43.02,
      "bbLowerMonth": 35.83,
      "bbMiddleMonth": 39.42,
      "bbPercentMonth": 0.747,
      "macdMonth": 0.9986,
      "signalMonth": 0.7711,
      "histogramMonth": 0.2274
    },
    {
      "symbol": "EVF",
      "date": "2026-04-30",
      "monthlyBars": 18,
      "rsi14Month": 34.97,
      "adx14Month": 50.67,
      "plusDiMonth": 26.83,
      "minusDiMonth": 13.12,
      "ma10Month": 12.88,
      "ma20Month": null,
      "ma50Month": null,
      "bbUpperMonth": 15.02,
      "bbLowerMonth": 10.74,
      "bbMiddleMonth": 12.88,
      "bbPercentMonth": 0.528,
      "macdMonth": 0.681,
      "signalMonth": 0.4726,
      "histogramMonth": 0.2084
    },
    {
      "symbol": "FCN",
      "date": "2026-04-30",
      "monthlyBars": 18,
      "rsi14Month": 75.7,
      "adx14Month": 49.66,
      "plusDiMonth": 23.74,
      "minusDiMonth": 22.4,
      "ma10Month": 14.68,
      "ma20Month": null,
      "ma50Month": null,
      "bbUpperMonth": 17.62,
      "bbLowerMonth": 11.74,
      "bbMiddleMonth": 14.68,
      "bbPercentMonth": 0.24,
      "macdMonth": 0.3152,
      "signalMonth": 0.5737,
      "histogramMonth": -0.2585
    },
    {
      "symbol": "FIT",
      "date": "2026-04-30",
      "monthlyBars": 18,
      "rsi14Month": 46.4,
      "adx14Month": 60.75,
      "plusDiMonth": 25.04,
      "minusDiMonth": 13.34,
      "ma10Month": 4.68,
      "ma20Month": null,
      "ma50Month": null,
      "bbUpperMonth": 5.2,
      "bbLowerMonth": 4.15,
      "bbMiddleMonth": 4.68,
      "bbPercentMonth": 0.012,
      "macdMonth": 0.0632,
      "signalMonth": 0.114,
      "histogramMonth": -0.0508
    },
    {
      "symbol": "FOX",
      "date": "2026-04-30",
      "monthlyBars": 18,
      "rsi14Month": 57.0,
      "adx14Month": 53.4,
      "plusDiMonth": 26.62,
      "minusDiMonth": 11.9,
      "ma10Month": 73.64,
      "ma20Month": null,
      "ma50Month": null,
      "bbUpperMonth": 97.0,
      "bbLowerMonth": 50.28,
      "bbMiddleMonth": 73.64,
      "bbPercentMonth": 0.653,
      "macdMonth": 5.0829,
      "signalMonth": 2.8146,
      "histogramMonth": 2.2683
    },
    {
      "symbol": "GIL",
      "date": "2026-04-30",
      "monthlyBars": 18,
      "rsi14Month": 20.11,
      "adx14Month": 69.13,
      "plusDiMonth": 8.8,
      "minusDiMonth": 23.96,
      "ma10Month": 15.56,
      "ma20Month": null,
      "ma50Month": null,
      "bbUpperMonth": 20.36,
      "bbLowerMonth": 10.77,
      "bbMiddleMonth": 15.56,
      "bbPercentMonth": 0.285,
      "macdMonth": -2.066,
      "signalMonth": -1.7271,
      "histogramMonth": -0.3389
    },
    {
      "symbol": "HAH",
      "date": "2026-04-30",
      "monthlyBars": 18,
      "rsi14Month": 61.85,
      "adx14Month": 87.07,
      "plusDiMonth": 31.19,
      "minusDiMonth": 3.26,
      "ma10Month": 57.9,
      "ma20Month": null,
      "ma50Month": null,
      "bbUpperMonth": 63.78,
      "bbLowerMonth": 52.02,
      "bbMiddleMonth": 57.9,
      "bbPercentMonth": 0.262,
      "macdMonth": 5.4108,
      "signalMonth": 5.2207,
      "histogramMonth": 0.1901
    },
    {
      "symbol": "HBC",
      "date": "2026-04-30",
      "monthlyBars": 18,
      "rsi14Month": 71.25,
      "adx14Month": 51.42,
      "plusDiMonth": 17.46,
      "minusDiMonth": 21.04,
      "ma10Month": 6.47,
      "ma20Month": null,
      "ma50Month": null,
      "bbUpperMonth": 8.34,
      "bbLowerMonth": 4.6,
      "bbMiddleMonth": 6.47,
      "bbPercentMonth": 0.107,
      "macdMonth": 0.0953,
      "signalMonth": 0.3237,
      "histogramMonth": -0.2284
    },
    {
      "symbol": "HDC",
      "date": "2026-04-30",
      "monthlyBars": 18,
      "rsi14Month": 35.78,
      "adx14Month": 48.56,
      "plusDiMonth": 21.23,
      "minusDiMonth": 28.04,
      "ma10Month": 25.59,
      "ma20Month": null,
      "ma50Month": null,
      "bbUpperMonth": 36.63,
      "bbLowerMonth": 14.55,
      "bbMiddleMonth": 25.59,
      "bbPercentMonth": 0.206,
      "macdMonth": -0.4615,
      "signalMonth": 0.4722,
      "histogramMonth": -0.9337
    },
    {
      "symbol": "HHS",
      "date": "2026-04-30",
      "monthlyBars": 18,
      "rsi14Month": 52.55,
      "adx14Month": 78.2,
      "plusDiMonth": 29.9,
      "minusDiMonth": 9.97,
      "ma10Month": 14.43,
      "ma20Month": null,
      "ma50Month": null,
      "bbUpperMonth": 19.39,
      "bbLowerMonth": 9.46,
      "bbMiddleMonth": 14.43,
      "bbPercentMonth": 0.356,
      "macdMonth": 1.3156,
      "signalMonth": 1.5538,
      "histogramMonth": -0.2382
    },
    {
      "symbol": "HPX",
      "date": "2026-04-30",
      "monthlyBars": 18,
      "rsi14Month": 42.62,
      "adx14Month": 51.67,
      "plusDiMonth": 21.27,
      "minusDiMonth": 18.7,
      "ma10Month": 5.04,
      "ma20Month": null,
      "ma50Month": null,
      "bbUpperMonth": 5.67,
      "bbLowerMonth": 4.41,
      "bbMiddleMonth": 5.04,
      "bbPercentMonth": 0.366,
      "macdMonth": 0.0612,
      "signalMonth": 0.0369,
      "histogramMonth": 0.0242
    },
    {
      "symbol": "HT1",
      "date": "2026-04-30",
      "monthlyBars": 18,
      "rsi14Month": 55.57,
      "adx14Month": 62.94,
      "plusDiMonth": 30.28,
      "minusDiMonth": 12.32,
      "ma10Month": 15.99,
      "ma20Month": null,
      "ma50Month": null,
      "bbUpperMonth": 18.39,
      "bbLowerMonth": 13.58,
      "bbMiddleMonth": 15.99,
      "bbPercentMonth": 0.254,
      "macdMonth": 1.1015,
      "signalMonth": 1.0153,
      "histogramMonth": 0.0862
    },
    {
      "symbol": "IDI",
      "date": "2026-04-30",
      "monthlyBars": 18,
      "rsi14Month": 32.08,
      "adx14Month": 53.89,
      "plusDiMonth": 16.76,
      "minusDiMonth": 21.06,
      "ma10Month": 7.23,
      "ma20Month": null,
      "ma50Month": null,
      "bbUpperMonth": 8.37,
      "bbLowerMonth": 6.09,
      "bbMiddleMonth": 7.23,
      "bbPercentMonth": 0.132,
      "macdMonth": -0.3695,
      "signalMonth": -0.3019,
      "histogramMonth": -0.0676
    },
    {
      "symbol": "LCG",
      "date": "2026-04-30",
      "monthlyBars": 18,
      "rsi14Month": 61.34,
      "adx14Month": 54.98,
      "plusDiMonth": 22.44,
      "minusDiMonth": 16.99,
      "ma10Month": 10.43,
      "ma20Month": null,
      "ma50Month": null,
      "bbUpperMonth": 11.82,
      "bbLowerMonth": 9.04,
      "bbMiddleMonth": 10.43,
      "bbPercentMonth": 0.327,
      "macdMonth": 0.2011,
      "signalMonth": 0.2152,
      "histogramMonth": -0.0141
    },
    {
      "symbol": "LHG",
      "date": "2026-04-30",
      "monthlyBars": 18,
      "rsi14Month": 30.74,
      "adx14Month": 50.46,
      "plusDiMonth": 15.56,
      "minusDiMonth": 27.23,
      "ma10Month": 29.79,
      "ma20Month": null,
      "ma50Month": null,
      "bbUpperMonth": 32.28,
      "bbLowerMonth": 27.31,
      "bbMiddleMonth": 29.79,
      "bbPercentMonth": 0.229,
      "macdMonth": -1.3489,
      "signalMonth": -1.1605,
      "histogramMonth": -0.1884
    },
    {
      "symbol": "MIG",
      "date": "2026-04-30",
      "monthlyBars": 18,
      "rsi14Month": 61.49,
      "adx14Month": 51.44,
      "plusDiMonth": 21.0,
      "minusDiMonth": 11.85,
      "ma10Month": 17.78,
      "ma20Month": null,
      "ma50Month": null,
      "bbUpperMonth": 19.78,
      "bbLowerMonth": 15.78,
      "bbMiddleMonth": 17.78,
      "bbPercentMonth": 0.456,
      "macdMonth": 0.7011,
      "signalMonth": 0.4824,
      "histogramMonth": 0.2187
    },
    {
      "symbol": "NBB",
      "date": "2026-04-30",
      "monthlyBars": 18,
      "rsi14Month": 15.83,
      "adx14Month": 49.21,
      "plusDiMonth": 13.14,
      "minusDiMonth": 16.86,
      "ma10Month": 19.76,
      "ma20Month": null,
      "ma50Month": null,
      "bbUpperMonth": 23.89,
      "bbLowerMonth": 15.64,
      "bbMiddleMonth": 19.76,
      "bbPercentMonth": 0.262,
      "macdMonth": -1.5282,
      "signalMonth": -1.1402,
      "histogramMonth": -0.3879
    },
    {
      "symbol": "NHA",
      "date": "2026-04-30",
      "monthlyBars": 18,
      "rsi14Month": 24.33,
      "adx14Month": 50.82,
      "plusDiMonth": 13.01,
      "minusDiMonth": 29.48,
      "ma10Month": 16.87,
      "ma20Month": null,
      "ma50Month": null,
      "bbUpperMonth": 22.61,
      "bbLowerMonth": 11.12,
      "bbMiddleMonth": 16.87,
      "bbPercentMonth": 0.159,
      "macdMonth": -1.9845,
      "signalMonth": -1.3607,
      "histogramMonth": -0.6238
    },
    {
      "symbol": "ORS",
      "date": "2026-04-30",
      "monthlyBars": 18,
      "rsi14Month": 51.82,
      "adx14Month": 50.63,
      "plusDiMonth": 20.88,
      "minusDiMonth": 16.34,
      "ma10Month": 13.75,
      "ma20Month": null,
      "ma50Month": null,
      "bbUpperMonth": 16.58,
      "bbLowerMonth": 10.93,
      "bbMiddleMonth": 13.75,
      "bbPercentMonth": 0.393,
      "macdMonth": 0.0332,
      "signalMonth": -0.105,
      "histogramMonth": 0.1382
    },
    {
      "symbol": "PHR",
      "date": "2026-04-30",
      "monthlyBars": 18,
      "rsi14Month": 54.96,
      "adx14Month": 42.12,
      "plusDiMonth": 22.77,
      "minusDiMonth": 16.34,
      "ma10Month": 59.4,
      "ma20Month": null,
      "ma50Month": null,
      "bbUpperMonth": 66.61,
      "bbLowerMonth": 52.19,
      "bbMiddleMonth": 59.4,
      "bbPercentMonth": 0.639,
      "macdMonth": 2.3361,
      "signalMonth": 1.672,
      "histogramMonth": 0.6641
    },
    {
      "symbol": "QCG",
      "date": "2026-04-30",
      "monthlyBars": 18,
      "rsi14Month": 35.69,
      "adx14Month": 47.64,
      "plusDiMonth": 26.56,
      "minusDiMonth": 16.58,
      "ma10Month": 13.93,
      "ma20Month": null,
      "ma50Month": null,
      "bbUpperMonth": 15.2,
      "bbLowerMonth": 12.65,
      "bbMiddleMonth": 13.93,
      "bbPercentMonth": 0.451,
      "macdMonth": 0.4012,
      "signalMonth": 0.2686,
      "histogramMonth": 0.1327
    },
    {
      "symbol": "SBT",
      "date": "2026-04-30",
      "monthlyBars": 18,
      "rsi14Month": 71.77,
      "adx14Month": 88.77,
      "plusDiMonth": 34.74,
      "minusDiMonth": 15.1,
      "ma10Month": 22.69,
      "ma20Month": null,
      "ma50Month": null,
      "bbUpperMonth": 24.86,
      "bbLowerMonth": 20.52,
      "bbMiddleMonth": 22.69,
      "bbPercentMonth": -0.04,
      "macdMonth": 2.9076,
      "signalMonth": 2.8821,
      "histogramMonth": 0.0254
    },
    {
      "symbol": "SCR",
      "date": "2026-04-30",
      "monthlyBars": 18,
      "rsi14Month": 54.08,
      "adx14Month": 57.09,
      "plusDiMonth": 19.88,
      "minusDiMonth": 21.92,
      "ma10Month": 7.87,
      "ma20Month": null,
      "ma50Month": null,
      "bbUpperMonth": 10.61,
      "bbLowerMonth": 5.13,
      "bbMiddleMonth": 7.87,
      "bbPercentMonth": 0.168,
      "macdMonth": 0.3123,
      "signalMonth": 0.5428,
      "histogramMonth": -0.2305
    },
    {
      "symbol": "SJS",
      "date": "2026-04-30",
      "monthlyBars": 18,
      "rsi14Month": 71.76,
      "adx14Month": 69.95,
      "plusDiMonth": 37.67,
      "minusDiMonth": 15.88,
      "ma10Month": 59.73,
      "ma20Month": null,
      "ma50Month": null,
      "bbUpperMonth": 74.4,
      "bbLowerMonth": 45.07,
      "bbMiddleMonth": 59.73,
      "bbPercentMonth": 0.431,
      "macdMonth": 7.8225,
      "signalMonth": 8.024,
      "histogramMonth": -0.2015
    },
    {
      "symbol": "SKG",
      "date": "2026-04-30",
      "monthlyBars": 18,
      "rsi14Month": 57.05,
      "adx14Month": 45.33,
      "plusDiMonth": 17.67,
      "minusDiMonth": 22.26,
      "ma10Month": 10.3,
      "ma20Month": null,
      "ma50Month": null,
      "bbUpperMonth": 11.63,
      "bbLowerMonth": 8.97,
      "bbMiddleMonth": 10.3,
      "bbPercentMonth": 0.218,
      "macdMonth": -0.2059,
      "signalMonth": -0.0638,
      "histogramMonth": -0.1421
    },
    {
      "symbol": "SLS",
      "date": "2026-04-30",
      "monthlyBars": 18,
      "rsi14Month": 54.05,
      "adx14Month": 60.07,
      "plusDiMonth": 11.44,
      "minusDiMonth": 35.6,
      "ma10Month": 166.02,
      "ma20Month": null,
      "ma50Month": null,
      "bbUpperMonth": 180.61,
      "bbLowerMonth": 151.43,
      "bbMiddleMonth": 166.02,
      "bbPercentMonth": 0.122,
      "macdMonth": -2.4252,
      "signalMonth": 0.2074,
      "histogramMonth": -2.6326
    },
    {
      "symbol": "TCH",
      "date": "2026-04-30",
      "monthlyBars": 18,
      "rsi14Month": 52.74,
      "adx14Month": 49.49,
      "plusDiMonth": 21.04,
      "minusDiMonth": 20.88,
      "ma10Month": 18.74,
      "ma20Month": null,
      "ma50Month": null,
      "bbUpperMonth": 23.04,
      "bbLowerMonth": 14.45,
      "bbMiddleMonth": 18.74,
      "bbPercentMonth": 0.431,
      "macdMonth": 1.1956,
      "signalMonth": 1.3289,
      "histogramMonth": -0.1333
    },
    {
      "symbol": "TIG",
      "date": "2026-04-30",
      "monthlyBars": 18,
      "rsi14Month": 27.43,
      "adx14Month": 54.35,
      "plusDiMonth": 13.63,
      "minusDiMonth": 29.82,
      "ma10Month": 8.34,
      "ma20Month": null,
      "ma50Month": null,
      "bbUpperMonth": 10.5,
      "bbLowerMonth": 6.18,
      "bbMiddleMonth": 8.34,
      "bbPercentMonth": 0.098,
      "macdMonth": -1.4415,
      "signalMonth": -1.2914,
      "histogramMonth": -0.1501
    },
    {
      "symbol": "TMS",
      "date": "2026-04-30",
      "monthlyBars": 19,
      "rsi14Month": 18.7,
      "adx14Month": 40.85,
      "plusDiMonth": 15.59,
      "minusDiMonth": 17.12,
      "ma10Month": 40.51,
      "ma20Month": null,
      "ma50Month": null,
      "bbUpperMonth": 41.58,
      "bbLowerMonth": 39.45,
      "bbMiddleMonth": 40.51,
      "bbPercentMonth": 0.376,
      "macdMonth": -0.2944,
      "signalMonth": -0.3722,
      "histogramMonth": 0.0778
    },
    {
      "symbol": "TNG",
      "date": "2026-04-30",
      "monthlyBars": 18,
      "rsi14Month": 52.0,
      "adx14Month": 57.74,
      "plusDiMonth": 22.22,
      "minusDiMonth": 13.38,
      "ma10Month": 20.63,
      "ma20Month": null,
      "ma50Month": null,
      "bbUpperMonth": 26.6,
      "bbLowerMonth": 14.66,
      "bbMiddleMonth": 20.63,
      "bbPercentMonth": 0.531,
      "macdMonth": 0.3122,
      "signalMonth": -0.279,
      "histogramMonth": 0.5912
    },
    {
      "symbol": "TV2",
      "date": "2026-04-30",
      "monthlyBars": 18,
      "rsi14Month": 63.95,
      "adx14Month": 46.89,
      "plusDiMonth": 20.47,
      "minusDiMonth": 12.74,
      "ma10Month": 35.91,
      "ma20Month": null,
      "ma50Month": null,
      "bbUpperMonth": 40.44,
      "bbLowerMonth": 31.39,
      "bbMiddleMonth": 35.91,
      "bbPercentMonth": 0.361,
      "macdMonth": 1.5261,
      "signalMonth": 1.3854,
      "histogramMonth": 0.1407
    },
    {
      "symbol": "VCG",
      "date": "2026-04-30",
      "monthlyBars": 18,
      "rsi14Month": 63.21,
      "adx14Month": 61.32,
      "plusDiMonth": 28.69,
      "minusDiMonth": 17.36,
      "ma10Month": 23.38,
      "ma20Month": null,
      "ma50Month": null,
      "bbUpperMonth": 29.2,
      "bbLowerMonth": 17.57,
      "bbMiddleMonth": 23.38,
      "bbPercentMonth": 0.394,
      "macdMonth": 1.4515,
      "signalMonth": 1.7376,
      "histogramMonth": -0.2862
    },
    {
      "symbol": "VGC",
      "date": "2026-04-30",
      "monthlyBars": 18,
      "rsi14Month": 56.93,
      "adx14Month": 51.8,
      "plusDiMonth": 25.95,
      "minusDiMonth": 17.5,
      "ma10Month": 49.07,
      "ma20Month": null,
      "ma50Month": null,
      "bbUpperMonth": 60.88,
      "bbLowerMonth": 37.26,
      "bbMiddleMonth": 49.07,
      "bbPercentMonth": 0.226,
      "macdMonth": 1.3608,
      "signalMonth": 1.8088,
      "histogramMonth": -0.448
    },
    {
      "symbol": "VIX",
      "date": "2026-04-30",
      "monthlyBars": 18,
      "rsi14Month": 51.98,
      "adx14Month": 64.38,
      "plusDiMonth": 28.6,
      "minusDiMonth": 17.81,
      "ma10Month": 22.02,
      "ma20Month": null,
      "ma50Month": null,
      "bbUpperMonth": 32.72,
      "bbLowerMonth": 11.32,
      "bbMiddleMonth": 22.02,
      "bbPercentMonth": 0.252,
      "macdMonth": 2.723,
      "signalMonth": 3.0561,
      "histogramMonth": -0.3331
    },
    {
      "symbol": "VOS",
      "date": "2026-04-30",
      "monthlyBars": 18,
      "rsi14Month": 65.78,
      "adx14Month": 49.5,
      "plusDiMonth": 23.1,
      "minusDiMonth": 8.85,
      "ma10Month": 13.32,
      "ma20Month": null,
      "ma50Month": null,
      "bbUpperMonth": 15.12,
      "bbLowerMonth": 11.51,
      "bbMiddleMonth": 13.32,
      "bbPercentMonth": 0.302,
      "macdMonth": -0.3115,
      "signalMonth": -0.2492,
      "histogramMonth": -0.0623
    },
    {
      "symbol": "VSC",
      "date": "2026-04-30",
      "monthlyBars": 18,
      "rsi14Month": 54.33,
      "adx14Month": 59.31,
      "plusDiMonth": 30.42,
      "minusDiMonth": 13.55,
      "ma10Month": 24.23,
      "ma20Month": null,
      "ma50Month": null,
      "bbUpperMonth": 31.33,
      "bbLowerMonth": 17.13,
      "bbMiddleMonth": 24.23,
      "bbPercentMonth": 0.297,
      "macdMonth": 2.673,
      "signalMonth": 2.6277,
      "histogramMonth": 0.0453
    }
  ],
  "errors": []
}