{"symbol":"HAX","date":"2026-04-29","price":10.25,"pivotDay":10.4,"supportDay":9.94,"resistanceDay":10.51,"supportDay2":10.18,"resistanceDay2":10.63,"supportLevelsDay":[9.9,9.4],"resistanceLevelsDay":[10.5,10.7,10.9,11.1,11.2],"nearSupportDay":9.9,"nextSupportDay":9.4,"nearResistanceDay":10.5,"nextResistanceDay":10.7,"activeSupportDay":9.9,"activeResistanceDay":10.5,"supportZoneDay":[9.89,9.99],"resistanceZoneDay":[10.46,10.56],"srStatusDay":"Trong vùng giao dịch","pivotWeek":10.58,"supportWeek":9.45,"resistanceWeek":10.89,"supportLevelsWeek":[9.4],"resistanceLevelsWeek":[10.9,12.0,12.8,13.8,14.3],"activeSupportWeek":9.4,"activeResistanceWeek":10.9,"srStatusWeek":"Trong vùng giao dịch","pivotMonth":12.01,"supportMonth":9.64,"resistanceMonth":13.59,"supportLevelsMonth":[9.6],"resistanceLevelsMonth":[13.6,15.0,16.9,18.2],"activeSupportMonth":9.6,"activeResistanceMonth":13.6,"srStatusMonth":"Trong vùng giao dịch","atr":0.2,"vwapDay":10.9,"donchianHighDay":12.2,"donchianLowDay":10.0,"donchianMidDay":11.1,"marketStructureDay":"Cấu trúc tăng","fibonacciLevelsDay":[14.11,13.22,12.5,11.78,10.76],"fibonacciLevelsWeek":[16.13,14.86,13.82,12.79,11.32],"fibonacciLevelsMonth":[16.13,14.86,13.82,12.79,11.32],"ma20Anchor":10.43,"ma50Anchor":10.64,"ma200Anchor":11.85,"ticker":"HAX"}